{
  "danceability" : 0.649,
  "energy" : 0.760,
  "key" : 1,
  "loudness" : -6.487,
  "mode" : 1,
  "speechiness" : 0.0574,
  "acousticness" : 0.114,
  "instrumentalness" : 0,
  "liveness" : 0.317,
  "valence" : 0.843,
  "tempo" : 80.018,
  "type" : "audio_features",
  "id" : "3ZozFqJJlDBNIm4xqxn2ZD",
  "uri" : "spotify:track:3ZozFqJJlDBNIm4xqxn2ZD",
  "track_href" : "https://api.spotify.com/v1/tracks/3ZozFqJJlDBNIm4xqxn2ZD",
  "analysis_url" : "https://api.spotify.com/v1/audio-analysis/3ZozFqJJlDBNIm4xqxn2ZD",
  "duration_ms" : 161853,
  "time_signature" : 4
}